Metadata-Version: 2.1
Name: sweep
Version: 2.1.3.0
Summary: SWeeP is a tool for representing large biologicalsequences in compact vectors
Home-page: https://github.com/diogomachado-bioinfo/sweep
Author: Diogo de J. S. Machado
Author-email: diogomachado.bioinfo@gmail.com
License: BSD-3-Clause
Requires-Dist: numpy
Requires-Dist: Biopython
Requires-Dist: scipy
Requires-Dist: tqdm
Requires-Dist: h5py
Requires-Dist: joblib
Requires-Dist: requests
